odoo/addons/sale_stock_available_info_popup/README.rst
odoo/addons/sale_stock_available_info_popup/__init__.py
odoo/addons/sale_stock_available_info_popup/__manifest__.py
odoo/addons/sale_stock_available_info_popup/i18n/es.po
odoo/addons/sale_stock_available_info_popup/i18n/hr.po
odoo/addons/sale_stock_available_info_popup/i18n/it.po
odoo/addons/sale_stock_available_info_popup/i18n/sale_stock_available_info_popup.pot
odoo/addons/sale_stock_available_info_popup/i18n/sl.po
odoo/addons/sale_stock_available_info_popup/models/__init__.py
odoo/addons/sale_stock_available_info_popup/models/sale_order.py
odoo/addons/sale_stock_available_info_popup/readme/CONTRIBUTORS.md
odoo/addons/sale_stock_available_info_popup/readme/DESCRIPTION.md
odoo/addons/sale_stock_available_info_popup/readme/USAGE.md
odoo/addons/sale_stock_available_info_popup/static/description/icon.png
odoo/addons/sale_stock_available_info_popup/static/description/index.html
odoo/addons/sale_stock_available_info_popup/static/src/xml/qty_at_date.xml
odoo/addons/sale_stock_available_info_popup/tests/__init__.py
odoo/addons/sale_stock_available_info_popup/tests/test_sale_stock_available_info_popup.py
odoo/addons/sale_stock_available_info_popup/views/sale_order_views.xml
odoo_addon_sale_stock_available_info_popup-17.0.1.0.0.2.dist-info/METADATA
odoo_addon_sale_stock_available_info_popup-17.0.1.0.0.2.dist-info/WHEEL
odoo_addon_sale_stock_available_info_popup-17.0.1.0.0.2.dist-info/top_level.txt
odoo_addon_sale_stock_available_info_popup-17.0.1.0.0.2.dist-info/RECORD
