Metadata-Version: 2.1
Name: odoo-addon-sale_stock_available_info_popup
Version: 17.0.1.0.0.2
Requires-Python: >=3.10
Requires-Dist: odoo-addon-stock_available>=17.0dev,<17.1dev
Requires-Dist: odoo>=17.0a,<17.1dev
Summary: Adds an 'Available to promise' quantity to the popover shown in sale order line that display stock info of the product
Home-page: https://github.com/OCA/stock-logistics-availability
License: AGPL-3
Author: Tecnativa, Odoo Community Association (OCA)
Author-email: support@odoo-community.org
Classifier: Programming Language :: Python
Classifier: Framework :: Odoo
Classifier: Framework :: Odoo :: 17.0
Classifier: License :: OSI Approved :: GNU Affero General Public License v3
